src/todo/__init__.py
src/todo/todo.py
src/todo/utils.py
todo_tje-0.1.0.dist-info/METADATA
todo_tje-0.1.0.dist-info/WHEEL
todo_tje-0.1.0.dist-info/licenses/LICENSE
todo_tje-0.1.0.dist-info/RECORD
