Metadata-Version: 2.1
Name: todo-tje
Version: 0.1.0
Summary: A command-line todo list.
Author: Tom Edwards
License-File: LICENSE
Classifier: License :: OSI Approved :: MIT License
Classifier: Operating System :: OS Independent
Classifier: Programming Language :: Python :: 3
Requires-Python: >=3.7
